a_pandas_ex_closest_neighbours/LICENSE
a_pandas_ex_closest_neighbours/README.MD
a_pandas_ex_closest_neighbours/__init__.py
a_pandas_ex_closest_neighbours/requirements.txt
a_pandas_ex_closest_neighbours/thirdparty.json
a_pandas_ex_closest_neighbours-0.10.dist-info/LICENSE.rst
a_pandas_ex_closest_neighbours-0.10.dist-info/METADATA
a_pandas_ex_closest_neighbours-0.10.dist-info/WHEEL
a_pandas_ex_closest_neighbours-0.10.dist-info/top_level.txt
a_pandas_ex_closest_neighbours-0.10.dist-info/RECORD
